[
  {
    "Theme\/Index":"Nifty Auto",
    "1 Day":0.37,
    "1 Week":0.49,
    "1 Month":5.67,
    "3 Months":2.7,
    "6 Months":6.13,
    "1 Year":31.04,
    "3 Years":121.63,
    "5 Years":231.99,
    "RS (5D)":0.63,
    "RS (10D)":2.76,
    "RS (20D)":3.89,
    "RS (50D)":4.05
  },
  {
    "Theme\/Index":"Nifty Bank",
    "1 Day":0.93,
    "1 Week":1.73,
    "1 Month":3.51,
    "3 Months":-5.62,
    "6 Months":7.88,
    "1 Year":22.14,
    "3 Years":69.17,
    "5 Years":171.13,
    "RS (5D)":0.65,
    "RS (10D)":2.2,
    "RS (20D)":-0.1,
    "RS (50D)":-3.23
  },
  {
    "Theme\/Index":"Nifty Consumer Durables",
    "1 Day":1.25,
    "1 Week":6.29,
    "1 Month":7.25,
    "3 Months":4.87,
    "6 Months":-10.35,
    "1 Year":-6.6,
    "3 Years":100.12,
    "5 Years":154.23,
    "RS (5D)":5.29,
    "RS (10D)":5.89,
    "RS (20D)":4.23,
    "RS (50D)":10.7
  },
  {
    "Theme\/Index":"Nifty Financial Services",
    "1 Day":0.69,
    "1 Week":2.21,
    "1 Month":3.28,
    "3 Months":-1.67,
    "6 Months":0.89,
    "1 Year":11.06,
    "3 Years":123.31,
    "5 Years":170.65,
    "RS (5D)":1.13,
    "RS (10D)":2.96,
    "RS (20D)":-0.32,
    "RS (50D)":1.14
  },
  {
    "Theme\/Index":"Nifty FMCG",
    "1 Day":3.15,
    "1 Week":4.05,
    "1 Month":3.43,
    "3 Months":-3.97,
    "6 Months":-7.23,
    "1 Year":-7.77,
    "3 Years":45.22,
    "5 Years":99.15,
    "RS (5D)":2.48,
    "RS (10D)":-0.22,
    "RS (20D)":-2.74,
    "RS (50D)":-1.68
  },
  {
    "Theme\/Index":"Nifty Healthcare",
    "1 Day":0.6,
    "1 Week":2.46,
    "1 Month":1.57,
    "3 Months":-0.38,
    "6 Months":-1.8,
    "1 Year":7.96,
    "3 Years":111.84,
    "5 Years":117.54,
    "RS (5D)":0.34,
    "RS (10D)":-3.76,
    "RS (20D)":-3.3,
    "RS (50D)":3.3
  },
  {
    "Theme\/Index":"Nifty IT",
    "1 Day":0.16,
    "1 Week":3.75,
    "1 Month":11.03,
    "3 Months":-16.51,
    "6 Months":-8.7,
    "1 Year":3.87,
    "3 Years":57.67,
    "5 Years":84.65,
    "RS (5D)":-0.67,
    "RS (10D)":1.67,
    "RS (20D)":7.08,
    "RS (50D)":-15.47
  },
  {
    "Theme\/Index":"Nifty Media",
    "1 Day":1.31,
    "1 Week":4.29,
    "1 Month":8.13,
    "3 Months":3.74,
    "6 Months":-0.04,
    "1 Year":4.95,
    "3 Years":45.02,
    "5 Years":82.87,
    "RS (5D)":3.74,
    "RS (10D)":1.97,
    "RS (20D)":6.0,
    "RS (50D)":5.74
  },
  {
    "Theme\/Index":"Nifty Metal",
    "1 Day":1.4,
    "1 Week":5.07,
    "1 Month":13.33,
    "3 Months":13.84,
    "6 Months":30.77,
    "1 Year":60.61,
    "3 Years":203.69,
    "5 Years":384.32,
    "RS (5D)":3.39,
    "RS (10D)":5.71,
    "RS (20D)":10.74,
    "RS (50D)":14.06
  },
  {
    "Theme\/Index":"Nifty Oil & Gas",
    "1 Day":2.67,
    "1 Week":4.3,
    "1 Month":5.36,
    "3 Months":0.87,
    "6 Months":0.34,
    "1 Year":8.43,
    "3 Years":85.82,
    "5 Years":156.75,
    "RS (5D)":2.74,
    "RS (10D)":1.0,
    "RS (20D)":0.06,
    "RS (50D)":0.63
  },
  {
    "Theme\/Index":"Nifty Pharma",
    "1 Day":0.6,
    "1 Week":1.73,
    "1 Month":1.18,
    "3 Months":1.95,
    "6 Months":3.72,
    "1 Year":11.92,
    "3 Years":134.15,
    "5 Years":108.55,
    "RS (5D)":-0.46,
    "RS (10D)":-4.61,
    "RS (20D)":-3.57,
    "RS (50D)":3.01
  },
  {
    "Theme\/Index":"Nifty PSU Bank",
    "1 Day":0.6,
    "1 Week":1.13,
    "1 Month":4.06,
    "3 Months":-3.16,
    "6 Months":8.57,
    "1 Year":24.68,
    "3 Years":100.26,
    "5 Years":296.19,
    "RS (5D)":0.09,
    "RS (10D)":1.36,
    "RS (20D)":-0.38,
    "RS (50D)":0.93
  },
  {
    "Theme\/Index":"Nifty Private Bank",
    "1 Day":0.88,
    "1 Week":1.82,
    "1 Month":4.31,
    "3 Months":-3.88,
    "6 Months":2.45,
    "1 Year":14.45,
    "3 Years":37.21,
    "5 Years":67.96,
    "RS (5D)":0.66,
    "RS (10D)":2.43,
    "RS (20D)":0.59,
    "RS (50D)":-2.92
  },
  {
    "Theme\/Index":"Nifty Realty",
    "1 Day":0.92,
    "1 Week":3.78,
    "1 Month":8.62,
    "3 Months":-7.5,
    "6 Months":-14.37,
    "1 Year":-3.9,
    "3 Years":133.21,
    "5 Years":318.64,
    "RS (5D)":3.08,
    "RS (10D)":8.74,
    "RS (20D)":8.08,
    "RS (50D)":2.26
  },
  {
    "Theme\/Index":"Agrochemicals & Fertilisers",
    "1 Day":0.82,
    "1 Week":3.08,
    "1 Month":9.25,
    "3 Months":-0.66,
    "6 Months":-7.81,
    "1 Year":-0.14,
    "3 Years":70.08,
    "5 Years":118.77,
    "RS (5D)":1.2,
    "RS (10D)":3.7,
    "RS (20D)":5.8,
    "RS (50D)":1.88
  },
  {
    "Theme\/Index":"Alcohols & Breweries",
    "1 Day":2.89,
    "1 Week":6.65,
    "1 Month":10.5,
    "3 Months":2.25,
    "6 Months":-13.17,
    "1 Year":-4.38,
    "3 Years":86.36,
    "5 Years":380.21,
    "RS (5D)":6.78,
    "RS (10D)":5.28,
    "RS (20D)":7.11,
    "RS (50D)":5.44
  },
  {
    "Theme\/Index":"AMC",
    "1 Day":3.34,
    "1 Week":5.17,
    "1 Month":11.3,
    "3 Months":12.41,
    "6 Months":4.49,
    "1 Year":50.61,
    "3 Years":232.16,
    "5 Years":182.43,
    "RS (5D)":6.05,
    "RS (10D)":7.49,
    "RS (20D)":9.0,
    "RS (50D)":16.23
  },
  {
    "Theme\/Index":"Auto Ancillary",
    "1 Day":1.07,
    "1 Week":2.06,
    "1 Month":6.31,
    "3 Months":5.24,
    "6 Months":5.03,
    "1 Year":34.26,
    "3 Years":108.15,
    "5 Years":250.68,
    "RS (5D)":1.32,
    "RS (10D)":0.8,
    "RS (20D)":4.28,
    "RS (50D)":6.76
  },
  {
    "Theme\/Index":"Auto Passenger & CV",
    "1 Day":0.05,
    "1 Week":-0.8,
    "1 Month":2.04,
    "3 Months":-5.21,
    "6 Months":12.98,
    "1 Year":32.41,
    "3 Years":125.21,
    "5 Years":224.24,
    "RS (5D)":-0.53,
    "RS (10D)":2.43,
    "RS (20D)":-0.39,
    "RS (50D)":-2.91
  },
  {
    "Theme\/Index":"Aviation",
    "1 Day":0.47,
    "1 Week":3.32,
    "1 Month":7.52,
    "3 Months":-0.31,
    "6 Months":-7.7,
    "1 Year":-1.31,
    "3 Years":92.46,
    "5 Years":198.01,
    "RS (5D)":2.15,
    "RS (10D)":4.64,
    "RS (20D)":3.74,
    "RS (50D)":6.24
  },
  {
    "Theme\/Index":"Building Materials",
    "1 Day":1.71,
    "1 Week":5.47,
    "1 Month":12.26,
    "3 Months":0.99,
    "6 Months":-15.24,
    "1 Year":2.49,
    "3 Years":27.79,
    "5 Years":95.21,
    "RS (5D)":4.79,
    "RS (10D)":7.4,
    "RS (20D)":11.52,
    "RS (50D)":3.05
  },
  {
    "Theme\/Index":"Capital Goods",
    "1 Day":1.78,
    "1 Week":5.03,
    "1 Month":10.63,
    "3 Months":17.39,
    "6 Months":15.32,
    "1 Year":31.55,
    "3 Years":146.01,
    "5 Years":505.35,
    "RS (5D)":4.86,
    "RS (10D)":4.73,
    "RS (20D)":6.87,
    "RS (50D)":15.96
  },
  {
    "Theme\/Index":"Capital Market",
    "1 Day":3.18,
    "1 Week":7.14,
    "1 Month":14.0,
    "3 Months":1.13,
    "6 Months":5.67,
    "1 Year":23.96,
    "3 Years":277.56,
    "5 Years":408.72,
    "RS (5D)":5.82,
    "RS (10D)":9.61,
    "RS (20D)":11.9,
    "RS (50D)":11.92
  },
  {
    "Theme\/Index":"Carbon and Graphite",
    "1 Day":0.75,
    "1 Week":8.63,
    "1 Month":15.22,
    "3 Months":4.57,
    "6 Months":2.3,
    "1 Year":2.81,
    "3 Years":120.14,
    "5 Years":89.06,
    "RS (5D)":6.4,
    "RS (10D)":4.82,
    "RS (20D)":12.17,
    "RS (50D)":9.57
  },
  {
    "Theme\/Index":"Cement",
    "1 Day":0.3,
    "1 Week":1.31,
    "1 Month":4.63,
    "3 Months":-9.66,
    "6 Months":-12.04,
    "1 Year":-6.43,
    "3 Years":27.28,
    "5 Years":36.43,
    "RS (5D)":0.51,
    "RS (10D)":0.47,
    "RS (20D)":0.75,
    "RS (50D)":-6.2
  },
  {
    "Theme\/Index":"Copper",
    "1 Day":1.55,
    "1 Week":9.12,
    "1 Month":20.33,
    "3 Months":23.05,
    "6 Months":58.54,
    "1 Year":114.3,
    "3 Years":297.25,
    "5 Years":497.24,
    "RS (5D)":7.3,
    "RS (10D)":13.21,
    "RS (20D)":17.61,
    "RS (50D)":20.62
  },
  {
    "Theme\/Index":"Critical Minerals",
    "1 Day":1.08,
    "1 Week":5.75,
    "1 Month":13.35,
    "3 Months":8.64,
    "6 Months":36.88,
    "1 Year":69.98,
    "3 Years":237.91,
    "5 Years":414.17,
    "RS (5D)":3.91,
    "RS (10D)":4.51,
    "RS (20D)":12.37,
    "RS (50D)":10.87
  },
  {
    "Theme\/Index":"Data Centre and AI",
    "1 Day":1.48,
    "1 Week":7.64,
    "1 Month":12.34,
    "3 Months":13.93,
    "6 Months":-6.68,
    "1 Year":33.09,
    "3 Years":498.91,
    "5 Years":1270.73,
    "RS (5D)":7.61,
    "RS (10D)":9.7,
    "RS (20D)":9.92,
    "RS (50D)":11.78
  },
  {
    "Theme\/Index":"Defence & Aerospace",
    "1 Day":2.42,
    "1 Week":8.41,
    "1 Month":12.63,
    "3 Months":16.9,
    "6 Months":10.91,
    "1 Year":38.96,
    "3 Years":296.36,
    "5 Years":1048.71,
    "RS (5D)":6.35,
    "RS (10D)":9.76,
    "RS (20D)":9.87,
    "RS (50D)":13.61
  },
  {
    "Theme\/Index":"Diagnostics & Pathology",
    "1 Day":-0.15,
    "1 Week":1.35,
    "1 Month":4.47,
    "3 Months":-4.65,
    "6 Months":-5.92,
    "1 Year":12.51,
    "3 Years":102.69,
    "5 Years":34.45,
    "RS (5D)":-0.41,
    "RS (10D)":1.87,
    "RS (20D)":-0.05,
    "RS (50D)":-3.49
  },
  {
    "Theme\/Index":"EV Ecosystem",
    "1 Day":0.32,
    "1 Week":1.09,
    "1 Month":7.54,
    "3 Months":8.44,
    "6 Months":10.9,
    "1 Year":33.98,
    "3 Years":147.29,
    "5 Years":330.04,
    "RS (5D)":1.98,
    "RS (10D)":4.0,
    "RS (20D)":8.32,
    "RS (50D)":8.48
  },
  {
    "Theme\/Index":"Fintech",
    "1 Day":1.15,
    "1 Week":6.0,
    "1 Month":8.96,
    "3 Months":-7.54,
    "6 Months":-9.42,
    "1 Year":4.19,
    "3 Years":158.57,
    "5 Years":183.24,
    "RS (5D)":4.68,
    "RS (10D)":5.81,
    "RS (20D)":7.48,
    "RS (50D)":-1.23
  },
  {
    "Theme\/Index":"FMCG Staples",
    "1 Day":2.36,
    "1 Week":2.98,
    "1 Month":4.17,
    "3 Months":-4.6,
    "6 Months":-5.65,
    "1 Year":7.11,
    "3 Years":35.85,
    "5 Years":78.95,
    "RS (5D)":1.42,
    "RS (10D)":-0.31,
    "RS (20D)":-1.06,
    "RS (50D)":-2.42
  },
  {
    "Theme\/Index":"Footwear",
    "1 Day":1.0,
    "1 Week":6.31,
    "1 Month":9.54,
    "3 Months":-9.54,
    "6 Months":-25.59,
    "1 Year":-17.78,
    "3 Years":-14.04,
    "5 Years":80.9,
    "RS (5D)":6.06,
    "RS (10D)":10.1,
    "RS (20D)":3.94,
    "RS (50D)":-11.6
  },
  {
    "Theme\/Index":"General Insurance",
    "1 Day":0.47,
    "1 Week":4.81,
    "1 Month":9.15,
    "3 Months":3.63,
    "6 Months":-6.49,
    "1 Year":5.73,
    "3 Years":83.42,
    "5 Years":35.55,
    "RS (5D)":5.51,
    "RS (10D)":3.7,
    "RS (20D)":4.44,
    "RS (50D)":2.41
  },
  {
    "Theme\/Index":"Green Hydrogen",
    "1 Day":0.28,
    "1 Week":5.38,
    "1 Month":9.43,
    "3 Months":12.71,
    "6 Months":5.62,
    "1 Year":8.55,
    "3 Years":104.31,
    "5 Years":264.09,
    "RS (5D)":3.71,
    "RS (10D)":6.33,
    "RS (20D)":5.12,
    "RS (50D)":17.51
  },
  {
    "Theme\/Index":"Hospitals",
    "1 Day":1.05,
    "1 Week":2.8,
    "1 Month":6.6,
    "3 Months":3.34,
    "6 Months":-10.36,
    "1 Year":8.91,
    "3 Years":149.78,
    "5 Years":377.26,
    "RS (5D)":1.25,
    "RS (10D)":0.64,
    "RS (20D)":2.92,
    "RS (50D)":7.16
  },
  {
    "Theme\/Index":"Hotels & Hospitality",
    "1 Day":0.78,
    "1 Week":3.9,
    "1 Month":8.94,
    "3 Months":-10.47,
    "6 Months":-19.56,
    "1 Year":-19.82,
    "3 Years":64.33,
    "5 Years":349.95,
    "RS (5D)":3.18,
    "RS (10D)":7.16,
    "RS (20D)":6.29,
    "RS (50D)":-6.24
  },
  {
    "Theme\/Index":"Housing Finance",
    "1 Day":1.24,
    "1 Week":4.91,
    "1 Month":10.36,
    "3 Months":-0.07,
    "6 Months":-4.74,
    "1 Year":-4.1,
    "3 Years":100.5,
    "5 Years":112.32,
    "RS (5D)":3.3,
    "RS (10D)":4.38,
    "RS (20D)":6.13,
    "RS (50D)":0.62
  },
  {
    "Theme\/Index":"Infrastructure & EPC",
    "1 Day":0.57,
    "1 Week":4.27,
    "1 Month":7.29,
    "3 Months":-0.42,
    "6 Months":-11.5,
    "1 Year":-7.92,
    "3 Years":62.18,
    "5 Years":145.89,
    "RS (5D)":3.28,
    "RS (10D)":2.1,
    "RS (20D)":4.13,
    "RS (50D)":1.56
  },
  {
    "Theme\/Index":"IT Services",
    "1 Day":-0.1,
    "1 Week":3.18,
    "1 Month":9.81,
    "3 Months":-20.25,
    "6 Months":-11.73,
    "1 Year":-0.72,
    "3 Years":40.73,
    "5 Years":92.36,
    "RS (5D)":-1.26,
    "RS (10D)":1.2,
    "RS (20D)":6.52,
    "RS (50D)":-18.03
  },
  {
    "Theme\/Index":"Jewellery & Gold",
    "1 Day":0.45,
    "1 Week":2.18,
    "1 Month":10.75,
    "3 Months":2.35,
    "6 Months":22.62,
    "1 Year":33.83,
    "3 Years":194.65,
    "5 Years":344.91,
    "RS (5D)":0.94,
    "RS (10D)":4.75,
    "RS (20D)":7.53,
    "RS (50D)":12.74
  },
  {
    "Theme\/Index":"Life Insurance",
    "1 Day":-0.5,
    "1 Week":2.9,
    "1 Month":-0.06,
    "3 Months":-6.81,
    "6 Months":-2.43,
    "1 Year":8.91,
    "3 Years":66.87,
    "5 Years":46.27,
    "RS (5D)":1.48,
    "RS (10D)":2.39,
    "RS (20D)":-3.91,
    "RS (50D)":-5.08
  },
  {
    "Theme\/Index":"Logistics",
    "1 Day":1.08,
    "1 Week":6.55,
    "1 Month":11.37,
    "3 Months":9.89,
    "6 Months":1.83,
    "1 Year":12.41,
    "3 Years":33.78,
    "5 Years":73.11,
    "RS (5D)":5.58,
    "RS (10D)":7.37,
    "RS (20D)":8.94,
    "RS (50D)":5.78
  },
  {
    "Theme\/Index":"Luxury",
    "1 Day":-0.06,
    "1 Week":1.86,
    "1 Month":11.33,
    "3 Months":0.12,
    "6 Months":-13.26,
    "1 Year":-8.3,
    "3 Years":97.13,
    "5 Years":261.48,
    "RS (5D)":0.73,
    "RS (10D)":3.17,
    "RS (20D)":8.57,
    "RS (50D)":5.35
  },
  {
    "Theme\/Index":"Marine & Offshore Services",
    "1 Day":1.79,
    "1 Week":4.9,
    "1 Month":4.37,
    "3 Months":12.91,
    "6 Months":51.61,
    "1 Year":52.37,
    "3 Years":135.81,
    "5 Years":253.1,
    "RS (5D)":1.98,
    "RS (10D)":-1.15,
    "RS (20D)":1.21,
    "RS (50D)":8.46
  },
  {
    "Theme\/Index":"Media & Broadcasting",
    "1 Day":1.58,
    "1 Week":5.89,
    "1 Month":15.61,
    "3 Months":3.32,
    "6 Months":-1.52,
    "1 Year":4.87,
    "3 Years":1.76,
    "5 Years":40.66,
    "RS (5D)":5.85,
    "RS (10D)":7.78,
    "RS (20D)":11.57,
    "RS (50D)":8.81
  },
  {
    "Theme\/Index":"Metals & Mining",
    "1 Day":1.58,
    "1 Week":3.72,
    "1 Month":8.56,
    "3 Months":12.18,
    "6 Months":28.51,
    "1 Year":52.11,
    "3 Years":153.55,
    "5 Years":286.28,
    "RS (5D)":0.86,
    "RS (10D)":1.99,
    "RS (20D)":4.5,
    "RS (50D)":11.58
  },
  {
    "Theme\/Index":"Music & Content",
    "1 Day":1.36,
    "1 Week":4.87,
    "1 Month":4.62,
    "3 Months":4.37,
    "6 Months":-0.94,
    "1 Year":-4.73,
    "3 Years":38.36,
    "5 Years":84.34,
    "RS (5D)":3.46,
    "RS (10D)":2.99,
    "RS (20D)":2.13,
    "RS (50D)":3.31
  },
  {
    "Theme\/Index":"NBFC",
    "1 Day":0.6,
    "1 Week":1.14,
    "1 Month":2.49,
    "3 Months":-2.56,
    "6 Months":5.49,
    "1 Year":17.18,
    "3 Years":146.76,
    "5 Years":220.37,
    "RS (5D)":-0.04,
    "RS (10D)":0.35,
    "RS (20D)":-1.66,
    "RS (50D)":1.95
  },
  {
    "Theme\/Index":"Oil & Gas Downstream",
    "1 Day":1.84,
    "1 Week":3.53,
    "1 Month":0.76,
    "3 Months":-4.05,
    "6 Months":3.47,
    "1 Year":17.78,
    "3 Years":181.77,
    "5 Years":257.68,
    "RS (5D)":0.9,
    "RS (10D)":-1.03,
    "RS (20D)":-7.03,
    "RS (50D)":-5.65
  },
  {
    "Theme\/Index":"Oil & Gas Midstream",
    "1 Day":3.26,
    "1 Week":6.42,
    "1 Month":9.69,
    "3 Months":2.93,
    "6 Months":-6.28,
    "1 Year":-4.08,
    "3 Years":31.17,
    "5 Years":93.87,
    "RS (5D)":5.86,
    "RS (10D)":5.53,
    "RS (20D)":4.17,
    "RS (50D)":3.6
  },
  {
    "Theme\/Index":"Oil & Gas Upstream",
    "1 Day":1.25,
    "1 Week":0.03,
    "1 Month":1.5,
    "3 Months":6.07,
    "6 Months":11.82,
    "1 Year":20.02,
    "3 Years":109.51,
    "5 Years":289.19,
    "RS (5D)":-2.55,
    "RS (10D)":-8.22,
    "RS (20D)":-2.54,
    "RS (50D)":2.15
  },
  {
    "Theme\/Index":"Packaging Solutions",
    "1 Day":0.81,
    "1 Week":3.81,
    "1 Month":3.66,
    "3 Months":9.04,
    "6 Months":-9.24,
    "1 Year":-6.19,
    "3 Years":29.57,
    "5 Years":86.07,
    "RS (5D)":2.34,
    "RS (10D)":3.59,
    "RS (20D)":2.29,
    "RS (50D)":12.03
  },
  {
    "Theme\/Index":"Paints",
    "1 Day":0.42,
    "1 Week":3.51,
    "1 Month":10.12,
    "3 Months":-8.64,
    "6 Months":-11.22,
    "1 Year":-9.45,
    "3 Years":6.52,
    "5 Years":-2.22,
    "RS (5D)":3.44,
    "RS (10D)":2.26,
    "RS (20D)":5.19,
    "RS (50D)":-0.08
  },
  {
    "Theme\/Index":"Paper",
    "1 Day":-0.24,
    "1 Week":5.02,
    "1 Month":9.19,
    "3 Months":2.43,
    "6 Months":-9.72,
    "1 Year":-4.65,
    "3 Years":-16.24,
    "5 Years":74.64,
    "RS (5D)":4.31,
    "RS (10D)":6.02,
    "RS (20D)":6.23,
    "RS (50D)":5.77
  },
  {
    "Theme\/Index":"Personal Care & Wellness",
    "1 Day":3.72,
    "1 Week":5.14,
    "1 Month":15.12,
    "3 Months":8.16,
    "6 Months":10.18,
    "1 Year":47.78,
    "3 Years":152.94,
    "5 Years":123.93,
    "RS (5D)":5.05,
    "RS (10D)":7.82,
    "RS (20D)":9.38,
    "RS (50D)":6.14
  },
  {
    "Theme\/Index":"Pharma Formulations",
    "1 Day":0.21,
    "1 Week":0.98,
    "1 Month":-1.6,
    "3 Months":0.73,
    "6 Months":-1.19,
    "1 Year":4.16,
    "3 Years":97.32,
    "5 Years":109.51,
    "RS (5D)":-1.14,
    "RS (10D)":-5.16,
    "RS (20D)":-6.88,
    "RS (50D)":1.58
  },
  {
    "Theme\/Index":"Power Generation",
    "1 Day":1.58,
    "1 Week":8.76,
    "1 Month":10.75,
    "3 Months":15.3,
    "6 Months":8.36,
    "1 Year":15.12,
    "3 Years":217.31,
    "5 Years":517.02,
    "RS (5D)":6.5,
    "RS (10D)":4.77,
    "RS (20D)":5.69,
    "RS (50D)":19.48
  },
  {
    "Theme\/Index":"Power T&D",
    "1 Day":2.59,
    "1 Week":5.32,
    "1 Month":13.41,
    "3 Months":30.44,
    "6 Months":12.67,
    "1 Year":49.55,
    "3 Years":429.08,
    "5 Years":1293.07,
    "RS (5D)":4.87,
    "RS (10D)":5.83,
    "RS (20D)":9.74,
    "RS (50D)":24.7
  },
  {
    "Theme\/Index":"Private Banking",
    "1 Day":0.88,
    "1 Week":1.82,
    "1 Month":4.31,
    "3 Months":-3.88,
    "6 Months":2.45,
    "1 Year":14.45,
    "3 Years":37.21,
    "5 Years":67.96,
    "RS (5D)":0.66,
    "RS (10D)":2.43,
    "RS (20D)":0.59,
    "RS (50D)":-2.92
  },
  {
    "Theme\/Index":"PSU Banking",
    "1 Day":0.6,
    "1 Week":1.13,
    "1 Month":4.06,
    "3 Months":-3.16,
    "6 Months":8.57,
    "1 Year":24.68,
    "3 Years":100.26,
    "5 Years":296.19,
    "RS (5D)":0.09,
    "RS (10D)":1.36,
    "RS (20D)":-0.38,
    "RS (50D)":0.93
  },
  {
    "Theme\/Index":"PVC Pipes & Plumbing",
    "1 Day":1.2,
    "1 Week":1.99,
    "1 Month":-1.59,
    "3 Months":24.44,
    "6 Months":4.81,
    "1 Year":10.62,
    "3 Years":28.39,
    "5 Years":54.06,
    "RS (5D)":-0.77,
    "RS (10D)":-0.63,
    "RS (20D)":-4.24,
    "RS (50D)":25.78
  },
  {
    "Theme\/Index":"QSR",
    "1 Day":-0.22,
    "1 Week":0.85,
    "1 Month":1.05,
    "3 Months":-12.43,
    "6 Months":-25.4,
    "1 Year":-31.51,
    "3 Years":-18.6,
    "5 Years":10.03,
    "RS (5D)":1.07,
    "RS (10D)":-1.33,
    "RS (20D)":-2.5,
    "RS (50D)":-6.29
  },
  {
    "Theme\/Index":"Railways & Infrastructure",
    "1 Day":2.15,
    "1 Week":8.07,
    "1 Month":11.86,
    "3 Months":-6.93,
    "6 Months":-11.65,
    "1 Year":-8.41,
    "3 Years":159.33,
    "5 Years":366.26,
    "RS (5D)":6.15,
    "RS (10D)":8.77,
    "RS (20D)":9.02,
    "RS (50D)":-4.11
  },
  {
    "Theme\/Index":"Renewable Energy",
    "1 Day":1.97,
    "1 Week":8.89,
    "1 Month":13.43,
    "3 Months":8.76,
    "6 Months":-1.73,
    "1 Year":-0.73,
    "3 Years":197.38,
    "5 Years":471.21,
    "RS (5D)":7.31,
    "RS (10D)":8.67,
    "RS (20D)":9.41,
    "RS (50D)":14.22
  },
  {
    "Theme\/Index":"Retail & E-Commerce",
    "1 Day":1.11,
    "1 Week":4.74,
    "1 Month":7.68,
    "3 Months":-1.69,
    "6 Months":-10.85,
    "1 Year":-1.74,
    "3 Years":65.0,
    "5 Years":159.06,
    "RS (5D)":3.32,
    "RS (10D)":1.97,
    "RS (20D)":5.19,
    "RS (50D)":2.73
  },
  {
    "Theme\/Index":"Semiconductors & EMS",
    "1 Day":1.44,
    "1 Week":8.46,
    "1 Month":12.47,
    "3 Months":14.97,
    "6 Months":-8.48,
    "1 Year":14.12,
    "3 Years":260.04,
    "5 Years":698.72,
    "RS (5D)":7.03,
    "RS (10D)":7.78,
    "RS (20D)":10.65,
    "RS (50D)":13.13
  },
  {
    "Theme\/Index":"Shipbuilding",
    "1 Day":4.02,
    "1 Week":11.13,
    "1 Month":14.55,
    "3 Months":16.82,
    "6 Months":6.05,
    "1 Year":36.7,
    "3 Years":550.07,
    "5 Years":1317.4,
    "RS (5D)":9.76,
    "RS (10D)":10.1,
    "RS (20D)":13.02,
    "RS (50D)":13.72
  },
  {
    "Theme\/Index":"Silver",
    "1 Day":1.19,
    "1 Week":5.39,
    "1 Month":13.74,
    "3 Months":7.43,
    "6 Months":36.4,
    "1 Year":62.54,
    "3 Years":191.22,
    "5 Years":366.17,
    "RS (5D)":3.37,
    "RS (10D)":6.03,
    "RS (20D)":8.24,
    "RS (50D)":11.98
  },
  {
    "Theme\/Index":"Solar Manufacturing",
    "1 Day":2.18,
    "1 Week":9.18,
    "1 Month":19.8,
    "3 Months":17.1,
    "6 Months":-10.06,
    "1 Year":4.59,
    "3 Years":407.66,
    "5 Years":950.2,
    "RS (5D)":9.33,
    "RS (10D)":10.57,
    "RS (20D)":25.91,
    "RS (50D)":25.66
  },
  {
    "Theme\/Index":"Specialty Chemicals",
    "1 Day":0.84,
    "1 Week":3.6,
    "1 Month":4.18,
    "3 Months":3.63,
    "6 Months":0.77,
    "1 Year":4.31,
    "3 Years":8.51,
    "5 Years":52.13,
    "RS (5D)":2.09,
    "RS (10D)":-0.7,
    "RS (20D)":0.41,
    "RS (50D)":3.71
  },
  {
    "Theme\/Index":"Sugar",
    "1 Day":1.42,
    "1 Week":2.7,
    "1 Month":15.2,
    "3 Months":18.69,
    "6 Months":3.88,
    "1 Year":1.71,
    "3 Years":3.94,
    "5 Years":172.41,
    "RS (5D)":0.5,
    "RS (10D)":-4.15,
    "RS (20D)":10.97,
    "RS (50D)":14.47
  },
  {
    "Theme\/Index":"Telecom Infra",
    "1 Day":0.79,
    "1 Week":0.79,
    "1 Month":5.38,
    "3 Months":17.97,
    "6 Months":6.01,
    "1 Year":-12.46,
    "3 Years":65.69,
    "5 Years":223.15,
    "RS (5D)":0.13,
    "RS (10D)":0.99,
    "RS (20D)":1.49,
    "RS (50D)":21.84
  },
  {
    "Theme\/Index":"Telecom Services",
    "1 Day":-0.47,
    "1 Week":1.16,
    "1 Month":1.15,
    "3 Months":-10.37,
    "6 Months":-5.6,
    "1 Year":12.18,
    "3 Years":92.8,
    "5 Years":120.61,
    "RS (5D)":-0.25,
    "RS (10D)":-0.1,
    "RS (20D)":-1.19,
    "RS (50D)":-8.44
  },
  {
    "Theme\/Index":"Textiles",
    "1 Day":1.84,
    "1 Week":4.6,
    "1 Month":11.06,
    "3 Months":4.54,
    "6 Months":-7.14,
    "1 Year":-10.67,
    "3 Years":24.06,
    "5 Years":117.02,
    "RS (5D)":3.15,
    "RS (10D)":2.67,
    "RS (20D)":9.4,
    "RS (50D)":3.76
  },
  {
    "Theme\/Index":"Two & Three Wheelers",
    "1 Day":0.28,
    "1 Week":-2.63,
    "1 Month":2.28,
    "3 Months":-0.33,
    "6 Months":2.08,
    "1 Year":35.1,
    "3 Years":167.17,
    "5 Years":267.32,
    "RS (5D)":-2.25,
    "RS (10D)":-1.49,
    "RS (20D)":-0.06,
    "RS (50D)":0.65
  },
  {
    "Theme\/Index":"Tyres & Rubber",
    "1 Day":1.61,
    "1 Week":2.86,
    "1 Month":5.4,
    "3 Months":-4.06,
    "6 Months":-4.13,
    "1 Year":15.88,
    "3 Years":71.22,
    "5 Years":122.62,
    "RS (5D)":1.35,
    "RS (10D)":1.15,
    "RS (20D)":1.42,
    "RS (50D)":-3.38
  },
  {
    "Theme\/Index":"Wealth Management",
    "1 Day":2.83,
    "1 Week":7.24,
    "1 Month":15.06,
    "3 Months":6.06,
    "6 Months":5.41,
    "1 Year":41.59,
    "3 Years":390.7,
    "5 Years":574.38,
    "RS (5D)":6.99,
    "RS (10D)":10.96,
    "RS (20D)":12.22,
    "RS (50D)":12.5
  },
  {
    "Theme\/Index":"White Goods",
    "1 Day":1.12,
    "1 Week":5.57,
    "1 Month":3.72,
    "3 Months":-1.59,
    "6 Months":-15.13,
    "1 Year":-14.2,
    "3 Years":31.12,
    "5 Years":33.03,
    "RS (5D)":4.12,
    "RS (10D)":2.67,
    "RS (20D)":-0.33,
    "RS (50D)":0.37
  },
  {
    "Theme\/Index":"Wires & Cables",
    "1 Day":2.13,
    "1 Week":5.64,
    "1 Month":9.83,
    "3 Months":12.76,
    "6 Months":6.7,
    "1 Year":28.37,
    "3 Years":95.09,
    "5 Years":486.25,
    "RS (5D)":5.04,
    "RS (10D)":5.88,
    "RS (20D)":8.03,
    "RS (50D)":13.07
  },
  {
    "Theme\/Index":"Nifty 50",
    "1 Day":0.69,
    "1 Week":1.89,
    "1 Month":4.08,
    "3 Months":-1.88,
    "6 Months":-0.47,
    "1 Year":9.32,
    "3 Years":80.61,
    "5 Years":149.66,
    "RS (5D)":0.0,
    "RS (10D)":0.0,
    "RS (20D)":0.0,
    "RS (50D)":0.0
  },
  {
    "Theme\/Index":"Nifty 500",
    "1 Day":1.33,
    "1 Week":4.11,
    "1 Month":8.13,
    "3 Months":2.03,
    "6 Months":-0.72,
    "1 Year":13.27,
    "3 Years":130.85,
    "5 Years":257.16,
    "RS (5D)":2.83,
    "RS (10D)":3.28,
    "RS (20D)":4.75,
    "RS (50D)":4.64
  },
  {
    "Theme\/Index":"Nifty Smallcap 250",
    "1 Day":1.5,
    "1 Week":4.85,
    "1 Month":9.96,
    "3 Months":2.94,
    "6 Months":-2.58,
    "1 Year":12.19,
    "3 Years":136.95,
    "5 Years":284.39,
    "RS (5D)":3.52,
    "RS (10D)":3.96,
    "RS (20D)":6.72,
    "RS (50D)":5.72
  }
]